data_connection/__init__.py
data_connection/abstract_side.py
data_connection/base_model.py
data_connection/field.py
data_connection/reader_side.py
data_connection/readers/__init__.py
data_connection/readers/mbtcp_client.py
data_connection/readers/opcua_client.py
data_connection/writer_side.py
data_connection-0.0.4.dist-info/WHEEL
data_connection-0.0.4.dist-info/METADATA
data_connection-0.0.4.dist-info/RECORD
