Metadata-Version: 2.1
Name: data-connection
Version: 0.0.4
Summary: Передача данных между сервисами
Home-page: https://github.com/Konstantin-Dudersky/data_exchange.git
Author: konstantin-dudersky
Author-email: konstantin.dudersky@gmail.com
Requires-Python: >=3.11,<3.12
Classifier: Programming Language :: Python :: 3
Classifier: Programming Language :: Python :: 3.11
Provides-Extra: modbus
Provides-Extra: opcua
Requires-Dist: asyncua (>=1.0.0,<2.0.0); extra == "opcua"
Requires-Dist: fastapi (<1.0.0)
Requires-Dist: pydantic (>=1.0.0,<2.0.0)
Requires-Dist: pymodbus (>=3.0.0,<4.0.0); extra == "modbus"
Requires-Dist: websockets (>=10.0.0,<11.0.0)
Project-URL: Repository, https://github.com/Konstantin-Dudersky/data_exchange.git
